[
  {
    "title": "Фестиваль Ticket to the sun",
    "description": "Розіграш унікальної прикраси з легендарного фестивалю Burning Man для ",
    "status": "Completed",
    "poster": "/images/news-pic-2.jpg",
    "videos": [""],
    "photos": [""],
    "locationsCount": "2",
    "partnersCount": "10",
    "events": [""]
  },
  {
    "title": "Фестиваль Ticket to the sun",
    "description": "Розіграш унікальної прикраси з легендарного фестивалю Burning Man для ",
    "status": "Completed",
    "poster": "/images/news-pic-2.jpg",
    "videos": [""],
    "photos": [""],
    "locationsCount": "2",
    "partnersCount": "10",
    "events": [""]
  },
  {
    "title": "Фестиваль Ticket to the sun",
    "description": "Розіграш унікальної прикраси з легендарного фестивалю Burning Man для ",
    "status": "Completed",
    "poster": "/images/news-pic-2.jpg",
    "videos": [""],
    "photos": [""],
    "locationsCount": "2",
    "partnersCount": "10",
    "events": [""]
  },
  {
    "title": "Фестиваль Ticket to the sun",
    "description": "Розіграш унікальної прикраси з легендарного фестивалю Burning Man для ",
    "status": "Completed",
    "poster": "/images/news-pic-2.jpg",
    "videos": [""],
    "photos": [""],
    "locationsCount": "2",
    "partnersCount": "10",
    "events": [""]
  },
  {
    "title": "Фестиваль Ticket to the sun",
    "description": "Розіграш унікальної прикраси з легендарного фестивалю Burning Man для ",
    "status": "Completed",
    "poster": "/images/news-pic-2.jpg",
    "videos": [""],
    "photos": [""],
    "locationsCount": "2",
    "partnersCount": "10",
    "events": [""]
  },
  {
    "title": "Фестиваль Ticket to the sun",
    "description": "Розіграш унікальної прикраси з легендарного фестивалю Burning Man для ",
    "status": "Completed",
    "poster": "/images/news-pic-2.jpg",
    "videos": [""],
    "photos": [""],
    "locationsCount": "2",
    "partnersCount": "10",
    "events": [""]
  }
]
